purple_titanium/__init__.py
purple_titanium/annotations.py
purple_titanium/context.py
purple_titanium/decorators.py
purple_titanium/events.py
purple_titanium/lazy_output.py
purple_titanium/persistence.py
purple_titanium/persistence_api.py
purple_titanium/persistence_backends.py
purple_titanium/serializers.py
purple_titanium/task.py
purple_titanium/task_executor.py
purple_titanium/task_factory.py
purple_titanium/task_mode.py
purple_titanium/task_signature.py
purple_titanium/task_state.py
purple_titanium/types.py
purple_titanium-0.1.5.dist-info/METADATA
purple_titanium-0.1.5.dist-info/WHEEL
purple_titanium-0.1.5.dist-info/RECORD
