Metadata-Version: 2.4
Name: purple-titanium
Version: 0.1.5
Summary: Pipeline framework for task-based data processing workflows.
Author-email: Gal Vinograd <gal.vinograd@gmail.com>
License: MIT
Requires-Python: >=3.10
Provides-Extra: dev
Requires-Dist: build>=1.0.0; extra == 'dev'
Requires-Dist: hatchling>=1.18.0; extra == 'dev'
Requires-Dist: pytest>=7.4.0; extra == 'dev'
Requires-Dist: ruff>=0.1.6; extra == 'dev'
Requires-Dist: twine>=6.1.0; extra == 'dev'
